{
  "ticker": "NFLX",
  "fiscal_year": "2024.0",
  "fiscal_quarter": "Q2",
  "summary": "Headline:\nNetflix delivered a solid Q2 with 12% revenue growth driven by subscriber gains and higher ARPU, alongside a 150 bps expansion in operating margin. The company raised full-year revenue guidance to low-teens growth and expects operating margin at the high end of its prior range.\n\nGrowth & revenue drivers:\n- Revenue increased 12% year-over-year.\n- Growth fueled by steady subscriber additions and higher average revenue per user (ARPU).\n- Content spend grew modestly, indicating disciplined investment in new titles.\n\nMargins / profitability:\n- Operating margin expanded by 150 basis points.\n- Improvement attributed to normalization of content amortization expenses.\n\nGuidance & outlook:\n- Full-year revenue guidance raised to low-teens percentage growth.\n- Operating margin expected to be at the high end of the previously communicated range.\n\nRisks / watchpoints:\n- No specific risks or challenges mentioned in the remarks.\n- Continued focus on disciplined content investment critical to sustaining margin expansion.",
  "meta": {
    "ticker": "NFLX",
    "company_hint": "NFLX 2024Q2 SAMPLE REMARKS",
    "fiscal_year": "2024.0",
    "fiscal_quarter": "Q2",
    "speaker": "CFO (preferred, with fallbacks)",
    "segment_count": 1,
    "source_docs": [
      "data/raw/NFLX_2024Q2_SAMPLE_REMARKS.txt"
    ]
  }
}